gray/__init__.py
gray/hooks.py
gray/main.py
gray/processing.py
gray/formatters/__init__.py
gray/formatters/add_trailing_comma.py
gray/formatters/autoflake.py
gray/formatters/base.py
gray/formatters/black.py
gray/formatters/composite.py
gray/formatters/fixit.py
gray/formatters/isort.py
gray/formatters/pyupgrade.py
gray/formatters/string_fixer.py
gray/formatters/trim.py
gray/utils/__init__.py
gray/utils/args.py
gray/vendors/__init__.py
gray/vendors/trim.py
gray-1.0.0.dist-info/licenses/AUTHORS.md
gray-1.0.0.dist-info/licenses/LICENSE
gray-1.0.0.dist-info/METADATA
gray-1.0.0.dist-info/WHEEL
gray-1.0.0.dist-info/entry_points.txt
gray-1.0.0.dist-info/top_level.txt
gray-1.0.0.dist-info/RECORD
