Metadata-Version: 2.4
Name: gray
Version: 1.0.0
Summary: Less uncompromising Python code formatter
Home-page: https://github.com/dizballanze/gray
Author: Yuri Shikanov
Author-email: dizballanze@gmail.com
License: MIT
Keywords: gray
Classifier: Development Status :: 2 - Pre-Alpha
Classifier: Intended Audience :: Developers
Classifier: License :: OSI Approved :: MIT License
Classifier: Natural Language :: English
Classifier: Programming Language :: Python :: 3.8
Classifier: Programming Language :: Python :: 3.9
Classifier: Programming Language :: Python :: 3.10
Classifier: Programming Language :: Python :: 3.11
Classifier: Programming Language :: Python :: 3.12
Classifier: Programming Language :: Python :: 3.13
Classifier: Programming Language :: Python :: 3 :: Only
Classifier: Topic :: Software Development :: Libraries :: Python Modules
Classifier: Topic :: Software Development :: Quality Assurance
License-File: LICENSE
License-File: AUTHORS.md
Requires-Dist: ConfigArgParse<2,>=1.5.3
Requires-Dist: add-trailing-comma>=2.2.1
Requires-Dist: autoflake~=1.5.3
Requires-Dist: black>=22.1.0
Requires-Dist: fixit>=2.1.0
Requires-Dist: isort>=5.10.1
Requires-Dist: pyupgrade>=2.31.0
Requires-Dist: rich<15,>=12.6
Requires-Dist: string_fixer>=0.5.0
Provides-Extra: develop
Requires-Dist: pylama~=8.4.1; extra == "develop"
Requires-Dist: pytest~=7.0.1; extra == "develop"
Requires-Dist: pytest-subtests~=0.7.0; extra == "develop"
Requires-Dist: wheel~=0.37.1; extra == "develop"
Requires-Dist: pre-commit~=2.12; extra == "develop"
Requires-Dist: setuptools; extra == "develop"
Dynamic: author
Dynamic: author-email
Dynamic: classifier
Dynamic: description
Dynamic: description-content-type
Dynamic: home-page
Dynamic: keywords
Dynamic: license
Dynamic: license-file
Dynamic: provides-extra
Dynamic: requires-dist
Dynamic: summary
